LICENSE
MANIFEST.in
README.md
requirements.txt
setup.cfg
setup.py
src/whisper_transcribe2/__init__.py
src/whisper_transcribe2/__main__.py
src/whisper_transcribe2/audio.py
src/whisper_transcribe2/decoding.py
src/whisper_transcribe2/model.py
src/whisper_transcribe2/timing.py
src/whisper_transcribe2/tokenizer.py
src/whisper_transcribe2/transcribe.py
src/whisper_transcribe2/triton_ops.py
src/whisper_transcribe2/utils.py
src/whisper_transcribe2/vad.py
src/whisper_transcribe2/version.py
src/whisper_transcribe2.egg-info/PKG-INFO
src/whisper_transcribe2.egg-info/SOURCES.txt
src/whisper_transcribe2.egg-info/dependency_links.txt
src/whisper_transcribe2.egg-info/entry_points.txt
src/whisper_transcribe2.egg-info/requires.txt
src/whisper_transcribe2.egg-info/top_level.txt
src/whisper_transcribe2/assets/__init__.py
src/whisper_transcribe2/assets/mel_filters.npz
src/whisper_transcribe2/assets/multilingual.tiktoken
src/whisper_transcribe2/assets/silero_vad.onnx
src/whisper_transcribe2/normalizers/english.json