Metadata-Version: 2.1
Name: whisper-transcribe2
Version: 1.2.2
Summary: Whisper command line client that uses CTranslate2 and faster-whisper to use different transcription styles
Home-page: https://github.com/fdorch/whisper-transcribe2
Author: Artem Fedorchenko
Author-email: iloaf13@outlook.com
License: MIT
Platform: UNKNOWN
Requires-Python: >=3.8
Provides-Extra: dev
License-File: LICENSE
